MANIFEST.in
README.txt
setup.py
docs/HISTORY.txt
docs/LICENSE.txt
src/silva/__init__.py
src/silva.captcha.egg-info/PKG-INFO
src/silva.captcha.egg-info/SOURCES.txt
src/silva.captcha.egg-info/dependency_links.txt
src/silva.captcha.egg-info/entry_points.txt
src/silva.captcha.egg-info/namespace_packages.txt
src/silva.captcha.egg-info/not-zip-safe
src/silva.captcha.egg-info/requires.txt
src/silva.captcha.egg-info/top_level.txt
src/silva/captcha/__init__.py
src/silva/captcha/arevmoit.bdf
src/silva/captcha/captcha.py
src/silva/captcha/configure.zcml
src/silva/captcha/field.py
src/silva/captcha/formulator.py
src/silva/captcha/ftesting.zcml
src/silva/captcha/helvi1.bdf
src/silva/captcha/waveIndex.zip
src/silva/captcha/zeamform.py
src/silva/captcha/tests/__init__.py
src/silva/captcha/tests/test_formulator.py
src/silva/captcha/zeamform_templates/captchafieldwidget.cpt