Metadata-Version: 1.1
Name: silva.captcha
Version: 1.3
Summary: Captcha support for Silva
Home-page: https://svn.infrae.com/silva.captcha/trunk
Author: Sylvain Viollon
Author-email: info@infrae.com
License: BSD
Keywords: captcha silva
Platform: UNKNOWN
Classifier: Framework :: Zope2
Classifier: Programming Language :: Python
Classifier: Topic :: Software Development :: Libraries :: Python Modules
Classifier: License :: OSI Approved :: BSD License
